{
  "messageId": "1527540905911914617",
  "transactions": [
    {
      "userId": "1390507432555581583",
      "type": "💳 Dépôt Validé",
      "game": "brut 5 000,00 €",
      "amount": 5000,
      "byId": "1521795461868949548",
      "at": 1784306929734
    },
    {
      "userId": "1521792561293951057",
      "type": "💳 Dépôt Validé",
      "game": "brut 1 500,00 €",
      "amount": 1500,
      "byId": "1521795461868949548",
      "at": 1784306924647
    },
    {
      "byId": "casino",
      "at": 1784304827638,
      "userId": "1390507432555581583",
      "type": "💀 Défaite Casino",
      "game": "Blackjack",
      "stake": 1500,
      "amount": -1500
    },
    {
      "userId": "1390507432555581583",
      "type": "💳 Dépôt Validé",
      "game": "brut 1 500,00 €",
      "amount": 1500,
      "byId": "1521795461868949548",
      "at": 1784304509515
    },
    {
      "byId": "casino",
      "at": 1784304016215,
      "userId": "1411724649036910673",
      "type": "💀 Défaite Casino",
      "game": "Blackjack",
      "stake": 100,
      "amount": -100
    },
    {
      "byId": "casino",
      "at": 1784303144143,
      "userId": "1521795564449173524",
      "type": "💀 Défaite Casino",
      "game": "Machine à sous",
      "stake": 5,
      "amount": -1.5
    },
    {
      "byId": "casino",
      "at": 1784303130256,
      "userId": "1521795564449173524",
      "type": "💀 Défaite Casino",
      "game": "Roulette",
      "stake": 600,
      "amount": -600
    },
    {
      "byId": "casino",
      "at": 1784303122507,
      "userId": "1521795564449173524",
      "type": "💀 Défaite Casino",
      "game": "Roulette",
      "stake": 2000,
      "amount": -2000
    },
    {
      "userId": "1521795564449173524",
      "type": "💸 Amende (Fraude ( Prend quelqu'un qui n'a pas passer la vérification casino sous prétexte que la personne n'a pas envie de jouer ))",
      "amount": -1500,
      "byId": "1390508824846139453",
      "at": 1784302588913
    },
    {
      "byId": "casino",
      "at": 1784302125926,
      "userId": "1411724649036910673",
      "type": "🏆 Victoire Casino",
      "game": "Blackjack",
      "stake": 100,
      "amount": 100
    },
    {
      "byId": "casino",
      "at": 1784301271380,
      "userId": "1411724649036910673",
      "type": "🏆 Victoire Casino",
      "game": "Blackjack",
      "stake": 100,
      "amount": 120
    },
    {
      "userId": "1484568600693178379",
      "type": "🔁 Virement envoyé",
      "game": "vers <@1521795564449173524>",
      "amount": -500,
      "byId": "1484568600693178379",
      "at": 1784300894296
    },
    {
      "userId": "1521795564449173524",
      "type": "🔁 Virement reçu",
      "game": "de <@1484568600693178379>",
      "amount": 375,
      "byId": "1484568600693178379",
      "at": 1784300894296
    },
    {
      "userId": "1509969106999443678",
      "type": "🏛️ Argent Taxe",
      "game": "virement",
      "amount": 125,
      "byId": "1484568600693178379",
      "at": 1784300894295
    },
    {
      "byId": "casino",
      "at": 1784300154198,
      "userId": "1521792561293951057",
      "type": "💀 Défaite Casino",
      "game": "Blackjack",
      "stake": 1500,
      "amount": -1500
    },
    {
      "byId": "casino",
      "at": 1784300141546,
      "userId": "1521792561293951057",
      "type": "💀 Défaite Casino",
      "game": "Blackjack",
      "stake": 2500,
      "amount": -2500
    },
    {
      "byId": "casino",
      "at": 1784300129587,
      "userId": "1521792561293951057",
      "type": "🏆 Victoire Casino",
      "game": "Blackjack",
      "stake": 2000,
      "amount": 0
    },
    {
      "byId": "casino",
      "at": 1784300110473,
      "userId": "1521792561293951057",
      "type": "🏆 Victoire Casino",
      "game": "Blackjack",
      "stake": 2000,
      "amount": 2000
    },
    {
      "byId": "casino",
      "at": 1784299861855,
      "userId": "320348102055690241",
      "type": "💀 Défaite Casino",
      "game": "Blackjack",
      "stake": 5000,
      "amount": -5000
    },
    {
      "byId": "casino",
      "at": 1784298568856,
      "userId": "1390507432555581583",
      "type": "💀 Défaite Casino",
      "game": "Blackjack",
      "stake": 2250,
      "amount": -2250
    },
    {
      "byId": "casino",
      "at": 1784298559521,
      "userId": "1390507432555581583",
      "type": "💀 Défaite Casino",
      "game": "Blackjack",
      "stake": 2500,
      "amount": -2500
    },
    {
      "userId": "1390507432555581583",
      "type": "💳 Dépôt Validé",
      "game": "brut 5 000,00 €",
      "amount": 4750,
      "byId": "1521795461868949548",
      "at": 1784297963435
    },
    {
      "userId": "1509969106999443678",
      "type": "🏛️ Argent Taxe",
      "game": "dépôt",
      "amount": 250,
      "byId": "1390507432555581583",
      "at": 1784297963435
    },
    {
      "byId": "casino",
      "at": 1784264748141,
      "userId": "1363979726418608148",
      "type": "💀 Défaite Casino",
      "game": "Roulette",
      "stake": 1500,
      "amount": -1500
    },
    {
      "byId": "casino",
      "at": 1784264739846,
      "userId": "1363979726418608148",
      "type": "🏆 Victoire Casino",
      "game": "Roulette",
      "stake": 750,
      "amount": 750
    },
    {
      "byId": "casino",
      "at": 1784264732039,
      "userId": "1363979726418608148",
      "type": "🏆 Victoire Casino",
      "game": "Roulette",
      "stake": 250,
      "amount": 250
    }
  ]
}